junky/__init__.py
junky/_version.py
junky/autotrain.py
junky/plotter.py
junky/supplements.py
junky/trainer.py
junky/utils.py
junky/dataset/__init__.py
junky/dataset/base_dataset.py
junky/dataset/bert_dataset.py
junky/dataset/bert_tokenized_dataset.py
junky/dataset/char_dataset.py
junky/dataset/dummy_dataset.py
junky/dataset/frame_dataset.py
junky/dataset/label_dataset.py
junky/dataset/len_dataset.py
junky/dataset/token_dataset.py
junky/dataset/word_cat_dataset.py
junky/dataset/word_dataset.py
junky/layers/__init__.py
junky/layers/char_emb_cnn.py
junky/layers/char_emb_rnn.py
junky/layers/highway_bilstm.py
junky/layers/highway_network.py
junky/layers/masking.py
junky-1.1.12.dist-info/LICENSE
junky-1.1.12.dist-info/METADATA
junky-1.1.12.dist-info/WHEEL
junky-1.1.12.dist-info/top_level.txt
junky-1.1.12.dist-info/RECORD
